heart/__init__.py
heart/cli.py
heart/heart.py
heart-0.1.0.dist-info/AUTHORS.rst
heart-0.1.0.dist-info/LICENSE
heart-0.1.0.dist-info/METADATA
heart-0.1.0.dist-info/WHEEL
heart-0.1.0.dist-info/entry_points.txt
heart-0.1.0.dist-info/top_level.txt
heart-0.1.0.dist-info/RECORD
