Metadata-Version: 2.1
Name: heart
Version: 0.1.0
Summary: HEART (Health Relationship Trust) Python implementation.
Home-page: https://github.com/nazrulworld/heart
Author: Md Nazrul Islam
Author-email: email2nazrul@gmail.com
License: GNU General Public License v3
Keywords: heart
Platform: UNKNOWN
Classifier: Development Status :: 2 - Pre-Alpha
Classifier: Intended Audience :: Developers
Classifier: License :: OSI Approved :: GNU General Public License v3 (GPLv3)
Classifier: Natural Language :: English
Classifier: Programming Language :: Python :: 3
Classifier: Programming Language :: Python :: 3.4
Classifier: Programming Language :: Python :: 3.5
Classifier: Programming Language :: Python :: 3.6
Classifier: Programming Language :: Python :: 3.7
Requires-Dist: Click (>=6.0)
Requires-Dist: guillotina (>=4.3.5)
Provides-Extra: test
Requires-Dist: coverage ; extra == 'test'
Requires-Dist: docker ; extra == 'test'
Requires-Dist: pytest ; extra == 'test'
Requires-Dist: pytest-asyncio ; extra == 'test'
Requires-Dist: pytest-cov ; extra == 'test'
Requires-Dist: pytest-docker-fixtures ; extra == 'test'
Requires-Dist: pytest-runner ; extra == 'test'
